daylio_parser/__init__.py
daylio_parser/config.py
daylio_parser/parser.py
daylio_parser/plot.py
daylio_parser/stats.py
daylio_parser-0.4.2.dist-info/LICENSE
daylio_parser-0.4.2.dist-info/METADATA
daylio_parser-0.4.2.dist-info/WHEEL
daylio_parser-0.4.2.dist-info/RECORD
