Metadata-Version: 2.1
Name: daylio-parser
Version: 0.4.2
Summary: A Python module to parse Daylio exports
Home-page: https://github.com/staticf0x/daylio-parser
License: MIT
Keywords: daylio,parser,stats
Author: staticf0x
Author-email: staticf0x@pm.me
Requires-Python: >=3.10,<3.13
Classifier: License :: OSI Approved :: MIT License
Classifier: Programming Language :: Python :: 3
Classifier: Programming Language :: Python :: 3.10
Classifier: Programming Language :: Python :: 3.11
Requires-Dist: numpy (>=1.26,<2.0)
Requires-Dist: pydantic (>=2.4.2,<3.0.0)
Project-URL: Documentation, https://daylio-parser.readthedocs.io/en/latest/
Project-URL: Repository, https://github.com/staticf0x/daylio-parser
